lie_learn/__init__.py
lie_learn/broadcasting.py
lie_learn/groups/SE2.py
lie_learn/groups/SO2.py
lie_learn/groups/SO3.c
lie_learn/groups/SO3.cpython-39-x86_64-linux-gnu.so
lie_learn/groups/SO3.pyx
lie_learn/groups/SO3_tests.py
lie_learn/groups/__init__.py
lie_learn/probability/HarmonicDensity.py
lie_learn/probability/S1HarmonicDensity.py
lie_learn/probability/S2HarmonicDensity.py
lie_learn/probability/SO3HarmonicDensity.py
lie_learn/probability/__init__.py
lie_learn/representations/__init__.py
lie_learn/representations/SO3/__init__.py
lie_learn/representations/SO3/clebsch_gordan_numerical.py
lie_learn/representations/SO3/indexing.py
lie_learn/representations/SO3/irrep_bases.c
lie_learn/representations/SO3/irrep_bases.cpython-39-x86_64-linux-gnu.so
lie_learn/representations/SO3/irrep_bases.pyx
lie_learn/representations/SO3/spherical_harmonics.py
lie_learn/representations/SO3/test_SO3_irrep_bases.py
lie_learn/representations/SO3/test_spherical_harmonics.py
lie_learn/representations/SO3/test_wigner_d.py
lie_learn/representations/SO3/wigner_d.py
lie_learn/representations/SO3/pinchon_hoggan/J_block_0-150.npy
lie_learn/representations/SO3/pinchon_hoggan/J_dense_0-150.npy
lie_learn/representations/SO3/pinchon_hoggan/__init__.py
lie_learn/representations/SO3/pinchon_hoggan/download.py
lie_learn/representations/SO3/pinchon_hoggan/pinchon_hoggan.c
lie_learn/representations/SO3/pinchon_hoggan/pinchon_hoggan.cpython-39-x86_64-linux-gnu.so
lie_learn/representations/SO3/pinchon_hoggan/pinchon_hoggan.pyx
lie_learn/representations/SO3/pinchon_hoggan/pinchon_hoggan_dense.py
lie_learn/representations/SO3/pinchon_hoggan/pinchon_hoggan_parsing.py
lie_learn/spaces/S2.py
lie_learn/spaces/S3.py
lie_learn/spaces/Tn.py
lie_learn/spaces/__init__.py
lie_learn/spaces/rn.py
lie_learn/spaces/spherical_quadrature.c
lie_learn/spaces/spherical_quadrature.cpython-39-x86_64-linux-gnu.so
lie_learn/spaces/spherical_quadrature.pyx
lie_learn/spectral/FFTBase.py
lie_learn_escience-0.0.5.dist-info/METADATA
lie_learn_escience-0.0.5.dist-info/WHEEL
lie_learn_escience-0.0.5.dist-info/top_level.txt
lie_learn_escience-0.0.5.dist-info/RECORD
lie_learn_escience-0.0.5.dist-info/licenses/LICENSE
