Metadata-Version: 2.4
Name: lie_learn_escience
Version: 0.0.5
Summary: A python package that knows how to do various tricky computations related to Lie groups and manifolds (mainly the sphere S2 and rotation group SO3).
Maintainer-email: Victor Azizi <v.azizi@esciencecenter.nl>
License: Copyright (c) 2017, Taco Cohen
Project-URL: Source Code, https://github.com/MALES-project/lie_learn2
Classifier: Programming Language :: Python :: 2.7
Classifier: Programming Language :: Python :: 3
Classifier: Programming Language :: Python :: 3.6
Classifier: Programming Language :: Python :: 3.7
Classifier: Programming Language :: Python :: 3.8
Classifier: Programming Language :: Python :: 3.9
Classifier: Programming Language :: Python :: 3.10
Classifier: Programming Language :: Python :: 3.11
Classifier: Programming Language :: Python :: 3.12
Classifier: Programming Language :: Python :: 3.14
Classifier: License :: OSI Approved :: MIT License
Classifier: Operating System :: OS Independent
Requires-Python: !=3.0.*,!=3.1.*,!=3.2.*,!=3.3.*,!=3.4.*,!=3.5.*,>2.7
License-File: LICENSE
Requires-Dist: requests
Requires-Dist: numpy<2; python_version >= "3.0"
Requires-Dist: scipy; python_version >= "3.0"
Requires-Dist: numpy<1.17; python_version < "3.0"
Requires-Dist: scipy<1.3; python_version < "3.0"
Dynamic: license-file
